Workbook

Sheet Cover
A3: Project Title: BlackRock Investment Analysis & Relative Valuation
A4: Company: BlackRock, Inc. (NYSE: BLK)
A5: Purpose: Analyze BlackRock’s financial performance, profitability, liquidity, leverage, efficiency, and investment attractiveness using public financial statements.
A6: Prepared by: Rushitha Anantha Sambhavi Galidevara

Sheet Income Statement
D2: BlackRock, Inc. (NYSE: BLK)
D3: Consolidated Statements of Income Analysis
D4: Fiscal Years 2025, 2024, and 2023
D5: (All amounts in millions of U.S. dollars, except per share data)
A7: Line Item | B7: FY 2025 | C7: FY 2024 | D7: FY 2023 | E7: FY25 vs FY24 (%) | F7: FY24 vs FY23 (%) | G7: Analysis
A8: Investment advisory, administration fees and securities lending revenue | B8: 19179 | C8: 16100 | D8: 14399 | E8: =(B8-C8)/C8 -> 0.19124224 | F8: =(C8-D8)/D8 -> 0.1181332 | G8: Strong revenue growth was driven by higher assets under management (AUM), favorable market performance, and sustained net client inflows.
A9: Investment advisory performance fees | B9: 1424 | C9: 1207 | D9: 554 | E9: =(B9-C9)/C9 -> 0.17978459 | F9: =(C9-D9)/D9 -> 1.1787004 | G9: Performance fees increased significantly as investment products outperformed benchmarks and generated higher incentive-based fees.
A10: Technology services revenue | B10: 1981 | C10: 1603 | D10: 1485 | E10: =(B10-C10)/C10 -> 0.23580786 | F10: =(C10-D10)/D10 -> 0.079461279 | G10: Revenue growth was supported by improved adoption of the Aladdin platform and expansion of technology solutions among institutional clients.
A11: Distribution fees | B11: 1355 | C11: 1273 | D11: 1262 | E11: =(B11-C11)/C11 -> 0.064414768 | F11: =(C11-D11)/D11 -> 0.0087163233 | G11: Stable growth was supported by strengthened distribution of investment products and continued client activity across global markets.
A12: Advisory and other revenue | B12: 277 | C12: 224 | D12: 159 | E12: =(B12-C12)/C12 -> 0.23660714 | F12: =(C12-D12)/D12 -> 0.40880503 | G12: Growth was driven by advisory engagements and additional client service offerings.
A13: Total Revenue | B13: =SUM(B8:B12) -> 24216 | C13: =SUM(C8:C12) -> 20407 | D13: =SUM(D8:D12) -> 17859 | E13: =(B13-C13)/C13 -> 0.18665164 | F13: =(C13-D13)/D13 -> 0.14267316 | G13: Total revenue increased 18.7% year-over-year, supported by higher assets under management, strong market appreciation, and positive net client inflows. Growth was broad-based across advisory, technology, and performance fee businesses.
A14: Employee compensation and benefits | B14: 8446 | C14: 6546 | D14: 5779 | E14: =(B14-C14)/C14 -> 0.29025359 | F14: =(C14-D14)/D14 -> 0.13272192 | G14: Compensation expensewas supported by higher incentive compensation, workforce expansion, and continued investment in talent.
A15: Distribution and servicing costs | B15: 2460 | C15: 2171 | D15: 2051 | E15: =(B15-C15)/C15 -> 0.13311838 | F15: =(C15-D15)/D15 -> 0.058508045 | G15: Costs benefited from higher distribution activity while remaining proportionate to revenue growth.
A16: Direct fund expense | B16: 1767 | C16: 1464 | D16: 1331 | E16: =(B16-C16)/C16 -> 0.20696721 | F16: =(C16-D16)/D16 -> 0.099924869 | G16: Higher fund activity and increased investment operations contributed to the rise in direct fund expenses.
A17: Sub-advisory and other | B17: 233 | C17: 140 | D17: 116 | E17: =(B17-C17)/C17 -> 0.66428571 | F17: =(C17-D17)/D17 -> 0.20689655 | G17: Growth reflects expanded utilization of third-party investment management and related services.
A18: General and administration | B18: 2731 | C18: 2257 | D18: 2092 | E18: =(B18-C18)/C18 -> 0.21001329 | F18: =(C18-D18)/D18 -> 0.078871893 | G18: Administrative expenses improved as BlackRock continued investing in technology, infrastructure, and global operations.
A19: Change in fair value of contingent consideration | B19: 720 | C19: -36 | D19: 3 | E19: N/M | F19: N/M | G19: Expense reflects remeasurement of acquisition-related contingent consideration and is not directly related to core operations.
A20: Restructuring charge | B20: 39 | C20: 0 | D20: 61 | E20: N/M | F20: =(C20-D20)/D20 -> -1 | G20: Minimal restructuring expense indicates limited organizational restructuring during the fiscal year.
A21: Amortization and impairment of intangible assets | B21: 775 | C21: 291 | D21: 151 | E21: =(B21-C21)/C21 -> 1.6632302 | F21: =(C21-D21)/D21 -> 0.92715232 | G21: Higher amortization primarily reflects acquired intangible assets associated with strategic acquisitions.
A22: Total Expense | B22: =SUM(B14:B21) -> 17171 | C22: =SUM(C14:C21) -> 12833 | D22: =SUM(D14:D21) -> 11584 | E22: =(B22-C22)/C22 -> 0.33803475 | F22: =(C22-D22)/D22 -> 0.10782113 | G22: Total expenses was driven primarily due to higher employee compensation, technology investments, and acquisition-related expenses.
A23: Operating Income | B23: =B13-B22 -> 7045 | C23: =C13-C22 -> 7574 | D23: =D13-D22 -> 6275 | E23: =(B23-C23)/C23 -> -0.069844204 | F23: =(C23-D23)/D23 -> 0.20701195 | G23: Operating income declined modestly as expense growth outpaced revenue growth during the period.
A24: Net gain (loss) on investments | B24: 634 | C24: 492 | D24: 699 | E24: =(B24-C24)/C24 -> 0.28861789 | F24: =(C24-D24)/D24 -> -0.29613734 | G24: Investment gains improved due to favorable market conditions and stronger portfolio performance.
A25: Interest and dividend income | B25: 554 | C25: 767 | D25: 473 | E25: =(B25-C25)/C25 -> -0.27770535 | F25: =(C25-D25)/D25 -> 0.62156448 | G25: Lower investment income reflects changes in portfolio composition and market interest rate dynamics.
A26: Interest expense | B26: -614 | C26: -538 | D26: -292 | E26: =(B26-C26)/C26 -> 0.14126394 | F26: =(C26-D26)/D26 -> 0.84246575 | G26: Higher borrowing costs and financing activities contributed to the increase in interest expense.
A27: Total nonoperating income (expense) | B27: =SUM(B24:B26) -> 574 | C27: =SUM(C24:C26) -> 721 | D27: =SUM(D24:D26) -> 880 | E27: =(B27-C27)/C27 -> -0.2038835 | F27: =(C27-D27)/D27 -> -0.18068182 | G27: Lower non-operating income reflects weaker investment returns and higher financing costs.
A28: Income Before Income Taxes | B28: =SUM(B23:B26) -> 7619 | C28: =SUM(C23:C26) -> 8295 | D28: =SUM(D23:D26) -> 7155 | E28: =(B28-C28)/C28 -> -0.081494876 | F28: =(C28-D28)/D28 -> 0.15932914 | G28: Pre-tax income declined modestly due to lower operating profitability and reduced non-operating income.
A29: Income tax expense | B29: 1677 | C29: 1783 | D29: 1479 | E29: =(B29-C29)/C29 -> -0.059450365 | F29: =(C29-D29)/D29 -> 0.20554429 | G29: Lower tax expense was primarily driven by reduced pre-tax earnings and changes in the effective tax rate.
A30: Net Income | B30: =B28-B29 -> 5942 | C30: =C28-C29 -> 6512 | D30: =D28-D29 -> 5676 | E30: =(B30-C30)/C30 -> -0.087530713 | F30: =(C30-D30)/D30 -> 0.14728682 | G30: Net income declined despite strong revenue growth as higher operating expenses reduced overall profitability.
A31: Diluted EPS | B31: 35.31 | C31: 42.01 | D31: 36.51 | E31: =(B31-C31)/C31 -> -0.15948584 | F31: =(C31-D31)/D31 -> 0.15064366 | G31: Earnings per share declined as lower net income offset the impact of share management activities.
A36: Executive Summary: • Revenue increased 18.7% YoY, driven by higher AUM and positive net client inflows. • Technology services continued to be a key growth driver, supported by continued Aladdin platform adoption. • Operating income declined 7.0% as expense growth outpaced revenue growth. • Net income decreased 8.8% despite strong top-line performance. • Continued investment in technology, infrastructure, and talent supports BlackRock's long-term growth strategy.
A38: Overall Assessment: BlackRock demonstrated strong top-line momentum in FY2025, driven by higher assets under management, robust client inflows, and continued growth in technology services. While higher operating expenses moderated profitability, the company's ongoing investments in technology, infrastructure, and strategic acquisitions strengthen its long-term competitive position.
A42: Source: BlackRock FY2025 Annual Report (Form 10-K), U.S. SEC.

Sheet Balance Sheet
D2: BlackRock, Inc. (NYSE: BLK)
B3: Consolidated Balance Sheet Analysis
B4: As of December 31, 2025, 2024, and 2023
D5: (All amounts in millions of U.S. dollars, except per share data)
A7: Line Item | B7: FY 2025 | C7: FY 2024 | D7: FY 2023 | E7: FY25 vs FY24 (%) | F7: FY24 vs FY23 (%) | G7: Analysis
A8: ASSETS
A9: Cash & Cash Equivalents | B9: 11468 | C9: 12762 | D9: 8736 | E9: =(B9-C9)/C9 -> -0.10139477 | F9: =(C9-D9)/D9 -> 0.46085165 | G9: Cash and cash equivalents declined 10.1% year-over-year, primarily reflecting cash deployed toward acquisitions, investments, and capital allocation activities despite continued strong operating cash generation.
A10: Accounts Receivables | B10: 5158 | C10: 4304 | D10: 3916 | E10: =(B10-C10)/C10 -> 0.19842007 | F10: =(C10-D10)/D10 -> 0.099080695 | G10: Accounts receivable increased due to higher advisory, technology, and investment-related revenues, resulting in greater outstanding receivables at year-end.
A11: Investments | B11: 13271 | C11: 9769 | D11: 9740 | E11: =(B11-C11)/C11 -> 0.35848091 | F11: =(C11-D11)/D11 -> 0.0029774127 | G11: Investments increased significantly, driven by portfolio appreciation, strategic investments, and assets acquired through business acquisitions.
A12: Separate account assets and collateral liabilities under securities lending agreements | B12: 68020 | C12: 58870 | D12: 60656 | E12: =(B12-C12)/C12 -> 0.15542721 | F12: =(C12-D12)/D12 -> -0.029444738 | G12: Separate account assets increased as a result of higher client assets under management and increased securities lending activity.
A13: Operating lease right-of-use assets | B13: 1874 | C13: 1519 | D13: 1421 | E13: =(B13-C13)/C13 -> 0.23370639 | F13: =(C13-D13)/D13 -> 0.068965517 | G13: Operating lease right-of-use assets increased due to new lease agreements and continued expansion of office facilities.
A14: Other assets | B14: 6956 | C14: 4699 | D14: 4960 | E14: =(B14-C14)/C14 -> 0.48031496 | F14: =(C14-D14)/D14 -> -0.052620968 | G14: Other assets increased primarily because of acquisition-related assets, higher deferred costs, and other investment-related balances.
A15: Subtotal | B15: =SUM(B9:B14) -> 106747 | C15: =SUM(C9:C14) -> 91923 | D15: =SUM(D9:D14) -> 89429 | E15: =(B15-C15)/C15 -> 0.16126541 | F15: =(C15-D15)/D15 -> 0.027888045 | G15: The increase in subtotal assets reflects broad-based growth across investment portfolios, client-related assets, and acquisition-related balances.
A16: Goodwill and Intangible Assets, Net | B16: 63251 | C16: 46692 | D16: 33782 | E16: =(B16-C16)/C16 -> 0.35464319 | F16: =(C16-D16)/D16 -> 0.38215618 | G16: Goodwill and intangible assets increased substantially following the acquisition of HPS Investment Partners, resulting in the recognition of acquired goodwill and identifiable intangible assets.
A17: Total Assets | B17: =SUM(B15:B16) -> 169998 | C17: =SUM(C15:C16) -> 138615 | D17: =SUM(D15:D16) -> 123211 | E17: =(B17-C17)/C17 -> 0.22640407 | F17: =(C17-D17)/D17 -> 0.1250213 | G17: Total assets increased 22.6% year-over-year, primarily driven by acquisition-related goodwill, higher investments, and growth in separate account assets.
A18: LIABILITIES
A19: Accrued compensation and benefits | B19: 3830 | C19: 2964 | D19: 2393 | E19: =(B19-C19)/C19 -> 0.29217274 | F19: =(C19-D19)/D19 -> 0.23861262 | G19: Accrued compensation and benefits increased due to higher employee incentive compensation, workforce expansion, and continued investment in talent.
A20: Accounts payable and accrued liabilities | B20: 1740 | C20: 1536 | D20: 1240 | E20: =(B20-C20)/C20 -> 0.1328125 | F20: =(C20-D20)/D20 -> 0.23870968 | G20: Accounts payable and accrued liabilities increased in line with higher operating activity and acquisition-related obligations.
A21: Borrowings | B21: 12768 | C21: 12314 | D21: 7918 | E21: =(B21-C21)/C21 -> 0.036868605 | F21: =(C21-D21)/D21 -> 0.5551907 | G21: Borrowings increased modestly, reflecting financing activities related to acquisitions and general corporate funding requirements.
A22: Separate account liabilities and collateral liabilities under securities lending agreements | B22: 68020 | C22: 58870 | D22: 60656 | E22: =(B22-C22)/C22 -> 0.15542721 | F22: =(C22-D22)/D22 -> -0.029444738 | G22: Separate account liabilities increased alongside separate account assets, reflecting higher client asset balances and securities lending activity.
A23: Contingent consideration liabilities | B23: 8429 | C23: 4302 | D23: 99 | E23: =(B23-C23)/C23 -> 0.95932125 | F23: N/M | G23: Contingent consideration liabilities increased significantly following acquisition-related earn-out obligations associated with HPS Investment Partners.
A24: Deferred income tax liabilities | B24: 4618 | C24: 3334 | D24: 3506 | E24: =(B24-C24)/C24 -> 0.38512298 | F24: =(C24-D24)/D24 -> -0.049058756 | G24: Deferred income tax liabilities increased primarily due to acquisition-related intangible assets and temporary tax differences.
A25: Operating lease liabilities | B25: 2228 | C25: 1908 | D25: 1784 | E25: =(B25-C25)/C25 -> 0.16771488 | F25: =(C25-D25)/D25 -> 0.069506726 | G25: Operating lease liabilities increased due to new lease commitments and lease renewals during the fiscal year.
A26: Other liabilities | B26: 6823 | C26: 4032 | D26: 4375 | E26: =(B26-C26)/C26 -> 0.6922123 | F26: =(C26-D26)/D26 -> -0.0784 | G26: Other liabilities increased primarily because of acquisition-related obligations, deferred compensation, and other operating liabilities.
A27: Total Liabilities | B27: =SUM(B19:B26) -> 108456 | C27: =SUM(C19:C26) -> 89260 | D27: =SUM(D19:D26) -> 81971 | E27: =(B27-C27)/C27 -> 0.21505714 | F27: =(C27-D27)/D27 -> 0.088921692 | G27: Total liabilities increased 21.5% year-over-year, reflecting acquisition-related obligations, higher compensation accruals, and increased operating liabilities.
A28: EQUITY
A29: Total BlackRock, Inc. stockholders’ equity | B29: 55888 | C29: 47495 | D29: 39347 | E29: =(B29-C29)/C29 -> 0.17671334 | F29: =(C29-D29)/D29 -> 0.20708059 | G29: Stockholders' equity increased due to higher retained earnings generated during the fiscal year despite shareholder capital distributions.
A30: Noncontrolling Interests | B30: 227 | C30: 169 | D30: 153 | E30: =(B30-C30)/C30 -> 0.34319527 | F30: =(C30-D30)/D30 -> 0.10457516 | G30: Noncontrolling interests increased as a result of higher ownership interests held by external investors in consolidated investment products.
A31: Total Equity | B31: =SUM(B29:B30) -> 56115 | C31: =SUM(C29:C30) -> 47664 | D31: =SUM(D29:D30) -> 39500 | E31: =(B31-C31)/C31 -> 0.17730363 | F31: =(C31-D31)/D31 -> 0.20668354 | G31: Total equity increased 17.7% year-over-year, supported by retained earnings growth and higher noncontrolling interests.
A32: TEMPORARY EQUITY
A33: Redeemable Noncontrolling Interests (NCI – CIPs) | B33: 5427 | C33: 1691 | D33: 1740 | E33: =(B33-C33)/C33 -> 2.2093436 | F33: =(C33-D33)/D33 -> -0.02816092 | G33: Redeemable noncontrolling interests increased significantly following the HPS acquisition and changes in ownership interests within consolidated investment products.
A34: Total Liabilities, Temporary Equity & Equity | B34: =SUM(B27+B31+B33) -> 169998 | C34: =SUM(C27+C31+C33) -> 138615 | D34: =SUM(D27+D31+D33) -> 123211 | E34: =(B34-C34)/C34 -> 0.22640407 | F34: =(C34-D34)/D34 -> 0.1250213 | G34: The combined balance increased 22.6% year-over-year, reflecting overall balance sheet expansion driven by strategic acquisitions, higher client assets, and continued business growth.
A39: Executive Summary: • Total assets increased 22.6% YoY, primarily driven by the acquisition of HPS Investment Partners, higher investments, and growth in separate account assets. • Goodwill and intangible assets rose significantly following acquisition-related asset recognition. • Total liabilities increased 21.5% due to acquisition-related obligations, higher compensation accruals, and increased operating liabilities. • Stockholders' equity grew 17.7%, supported by retained earnings and continued profitability. • The balance sheet reflects BlackRock's strategic expansion while maintaining a strong capital position.
A41: Overall Assessment BlackRock's balance sheet strengthened materially in FY2025, driven primarily by the HPS Investment Partners acquisition, higher investments, and continued growth in client-related assets. While liabilities increased alongside the company's strategic expansion, equity continued to grow through retained earnings, demonstrating strong financial flexibility and reinforcing BlackRock's long-term growth strategy.
A45: Source: BlackRock, Inc. FY2025 Annual Report (Form 10-K), Consolidated Balance Sheets, U.S. Securities and Exchange Commission (SEC).

Sheet Cash Flow Statement
D2: BlackRock, Inc. (NYSE: BLK)
D3: Consolidated Statements of Cash Flows Analysis
D4: Fiscal Years 2025, 2024, and 2023
D5: (All amounts in millions of U.S. dollars)
A7: Line Item | B7: FY 2025 | C7: FY 2024 | D7: FY 2023 | E7: FY25 vs FY24 (%) | F7: FY24 vs FY23 (%) | G7: Analysis
A8: OPERATING ACTIVITIES
A9: Net income | B9: 5942 | C9: 6512 | D9: 5676 | E9: =(B9-C9)/C9 -> -0.087530713 | F9: =(C9-D9)/D9 -> 0.14728682 | G9: Net income declined 8.8% year-over-year, reflecting higher operating expenses and acquisition-related costs despite continued revenue growth across BlackRock's core businesses.
A10: Depreciation and Amortization | B10: 1126 | C10: 529 | D10: 427 | E10: =(B10-C10)/C10 -> 1.1285444 | F10: =(C10-D10)/D10 -> 0.23887588 | G10: Depreciation and amortization more than doubled following the acquisition of HPS Investment Partners and the recognition of additional amortizable intangible assets.
A11: Stock-based compensation | B11: 1307 | C11: 753 | D11: 630 | E11: =(B11-C11)/C11 -> 0.73572377 | F11: =(C11-D11)/D11 -> 0.1952381 | G11: Stock-based compensation increased significantly as BlackRock continued investing in employee retention, performance incentives, and workforce expansion.
A12: Deferred income tax expense (benefit) | B12: -631 | C12: -106 | D12: 124 | E12: N/M | F12: N/M | G12: Deferred tax benefit increased due to changes in temporary tax differences, acquisition-related tax adjustments, and the recognition of deferred tax assets and liabilities.
A13: Change in fair value of contingent consideration | B13: 720 | C13: -36 | D13: 3 | E13: N/M | F13: N/M | G13: The increase reflects the remeasurement of contingent consideration liabilities associated with acquisition-related earn-out obligations, primarily related to the HPS acquisition.
A14: Other investment gains | B14: -289 | C14: -126 | D14: 0 | E14: =(B14-C14)/C14 -> 1.2936508 | F14: N/M | G14: Other investment gains primarily reflect changes in the fair value of BlackRock's investment portfolio and realized gains or losses on strategic investments.
A15: Net purchases/proceeds within CIPs | B15: -4214 | C15: -2672 | D15: -1780 | E15: =(B15-C15)/C15 -> 0.57709581 | F15: =(C15-D15)/D15 -> 0.5011236 | G15: Net cash outflows increased as consolidated investment products recorded higher investment purchases and portfolio activity during the fiscal year.
A16: Net cash provided by operating activities | B16: 3927 | C16: 4956 | D16: 4165 | E16: =(B16-C16)/C16 -> -0.20762712 | F16: =(C16-D16)/D16 -> 0.18991597 | G16: Operating cash flow decreased 20.8% year-over-year despite strong profitability, primarily reflecting higher working capital requirements and acquisition-related cash adjustments.
A17: INVESTING ACTIVITIES
A18: Purchases of investments | B18: -1384 | C18: -818 | D18: -846 | E18: =(B18-C18)/C18 -> 0.69193154 | F18: =(C18-D18)/D18 -> -0.033096927 | G18: Investment purchases increased as BlackRock continued allocating capital into strategic investments and investment portfolios.
A19: Proceeds from sales/maturities of investments | B19: 544 | C19: 766 | D19: 400 | E19: =(B19-C19)/C19 -> -0.28981723 | F19: =(C19-D19)/D19 -> 0.915 | G19: Cash proceeds from investment sales and maturities declined, reflecting fewer asset disposals during the fiscal year.
A20: Distributions of capital from equity method investees | B20: 390 | C20: 366 | D20: 46 | E20: =(B20-C20)/C20 -> 0.06557377 | F20: =(C20-D20)/D20 -> 6.9565217 | G20: Higher capital distributions from equity method investments contributed positively to investing cash flows.
A21: Net consolidations (deconsolidations) of sponsored investment funds | B21: -97 | C21: -127 | D21: -26 | E21: =(B21-C21)/C21 -> -0.23622047 | F21: =(C21-D21)/D21 -> 3.8846154 | G21: Cash flows from sponsored investment funds reflect ongoing portfolio restructuring and changes in consolidated investment vehicles.
A22: Acquisitions, net of cash acquired | B22: -3496 | C22: -2936 | D22: -189 | E22: =(B22-C22)/C22 -> 0.19073569 | F22: =(C22-D22)/D22 -> 14.534392 | G22: Investing cash outflows increased significantly due to the acquisition of HPS Investment Partners, representing BlackRock's largest strategic investment during the year.
A23: Capital expenditures | B23: -375 | C23: -255 | D23: -344 | E23: =(B23-C23)/C23 -> 0.47058824 | F23: =(C23-D23)/D23 -> -0.25872093 | G23: Capital expenditures increased to support technology infrastructure, office facilities, and long-term business expansion initiatives.
A24: Net cash used in investing activities | B24: -4418 | C24: -3004 | D24: -959 | E24: =(B24-C24)/C24 -> 0.47070573 | F24: =(C24-D24)/D24 -> 2.1324296 | G24: Investing cash outflows increased substantially, primarily driven by acquisition-related payments and continued investment activity.
A25: FINANCING ACTIVITIES
A26: Repayments of long-term borrowings | B26: -796 | C26: -1000 | D26: 0 | E26: =(B26-C26)/C26 -> -0.204 | F26: N/M | G26: BlackRock continued repaying outstanding debt as part of its long-term capital management strategy.
A27: Proceeds from long-term borrowings | B27: 1080 | C27: 5474 | D27: 1238 | E27: =(B27-C27)/C27 -> -0.80270369 | F27: =(C27-D27)/D27 -> 3.4216478 | G27: Borrowing activity declined significantly compared with the prior year, indicating reduced reliance on external financing after acquisition funding.
A28: Dividends/Subco distributions paid | B28: -3347 | C28: -3101 | D28: -3035 | E28: =(B28-C28)/C28 -> 0.079329249 | F28: =(C28-D28)/D28 -> 0.021746293 | G28: Dividend payments increased as BlackRock maintained its commitment to returning capital to shareholders.
A29: Shares/Subco Units repurchased | B29: -1951 | C29: -1930 | D29: -1884 | E29: =(B29-C29)/C29 -> 0.010880829 | F29: =(C29-D29)/D29 -> 0.024416136 | G29: Share repurchases remained relatively stable, demonstrating continued capital return through buyback programs.
A30: Net subscriptions received/(redemptions/distributions paid) from noncontrolling interest holders | B30: 3827 | C30: 2405 | D30: 1627 | E30: =(B30-C30)/C30 -> 0.59126819 | F30: =(C30-D30)/D30 -> 0.4781807 | G30: Higher net subscriptions reflected increased investor participation in consolidated sponsored investment products.
A31: Net cash used in financing activities | B31: -1127 | C31: 2236 | D31: -1992 | E31: N/M | F31: N/M | G31: Financing activities shifted to a net cash outflow as lower borrowing activity and continued shareholder distributions exceeded financing inflows.
A32: CASH RECONCILIATION
A33: Effect of exchange rate changes on cash, cash equivalents and restricted cash | B33: 329 | C33: -162 | D33: 106 | E33: N/M | F33: N/M | G33: Exchange rate movements had a favorable impact on cash balances during FY2025 compared with the unfavorable impact recorded in FY2024.
A34: Net increase/(decrease) in cash, cash equivalents and restricted cash | B34: -1289 | C34: 4026 | D34: 1320 | E34: N/M | F34: N/M | G34: Cash balances declined as investing cash outflows—primarily related to acquisitions and strategic investments—exceeded operating cash inflows.
A35: Cash, cash equivalents and restricted cash, beginning of year | B35: 12779 | C35: 8753 | D35: 7433 | E35: =(B35-C35)/C35 -> 0.45995659 | F35: =(C35-D35)/D35 -> 0.17758644 | G35: Beginning cash balance increased from the prior year, providing strong liquidity entering FY2025.
A36: Cash, cash equivalents and restricted cash, end of year | B36: 11490 | C36: 12779 | D36: 8753 | E36: =(B36-C36)/C36 -> -0.10086861 | F36: =(C36-D36)/D36 -> 0.45995659 | G36: Ending cash balances remained strong despite significant acquisition-related cash outflows, reflecting BlackRock's solid liquidity position.
A41: Executive Summary: • Operating cash flow remained healthy at $3.9 billion, although it declined due to acquisition-related adjustments and working capital movements. • Investing cash outflows increased 47.1% YoY, primarily driven by the acquisition of HPS Investment Partners and continued investment purchases. • Financing activities shifted to a net cash outflow as BlackRock reduced borrowing while maintaining dividends and share repurchases. • Cash balances declined 10.1% year-over-year, reflecting disciplined deployment of capital toward strategic investments. • Overall, the cash flow statement demonstrates BlackRock's focus on long-term growth through acquisitions while maintaining strong operating cash generation and shareholder returns.
A43: Overall Assessment: BlackRock generated strong operating cash flows while deploying significant capital toward strategic acquisitions and long-term investments during FY2025. Although cash balances declined because of increased investing activity, the company maintained solid liquidity and continued returning capital to shareholders through dividends and share repurchases. Overall, the cash flow profile reflects disciplined capital allocation, financial flexibility, and a long-term growth strategy supported by resilient operating performance.
A47: Source: BlackRock, Inc. Annual Reports (Forms 10-K), Fiscal Years 2025, 2024, and 2023. Consolidated Statements of Cash Flows. U.S. Securities and Exchange Commission (SEC).

Sheet Supporting Calculations
C2: BlackRock, Inc. (NYSE: BLK)
C3: Supporting Calculations
C4: Fiscal Years 2025, 2024, and 2023
C5: (All amounts in millions of U.S. dollars, except per share data)
A7: Section 1 - Income Statement Inputs
A8: Metric | B8: FY 2025 | C8: FY 2024 | D8: FY 2023 | E8: Formula / Source
A9: Total Revenue | B9: ='Income Statement'!B13 -> 24216 | C9: ='Income Statement'!C13 -> 20407 | D9: ='Income Statement'!D13 -> 17859 | E9: Income Statement
A10: Operating Income | B10: ='Income Statement'!B23 -> 7045 | C10: ='Income Statement'!C23 -> 7574 | D10: ='Income Statement'!D23 -> 6275 | E10: Income Statement
A11: Operating Margin (%) | B11: =B10/B9 -> 0.29092336 | C11: =C10/C9 -> 0.37114716 | D11: =D10/D9 -> 0.35136346 | E11: Calculated
A12: Net Income | B12: ='Income Statement'!B30 -> 5942 | C12: ='Income Statement'!C30 -> 6512 | D12: ='Income Statement'!D30 -> 5676 | E12: Income Statement
A13: Diluted EPS | B13: ='Income Statement'!B31 -> 35.31 | C13: ='Income Statement'!C31 -> 42.01 | D13: ='Income Statement'!D31 -> 36.51 | E13: Income Statement
A15: Section 2 - Balance Sheet Inputs
A16: Metric | B16: FY 2025 | C16: FY 2024 | D16: FY 2023 | E16: Formula/Source
A17: Cash & Cash Equivalents | B17: ='Balance Sheet'!B9 -> 11468 | C17: ='Balance Sheet'!C9 -> 12762 | D17: ='Balance Sheet'!D9 -> 8736 | E17: Balance Sheet
A18: Investments | B18: ='Balance Sheet'!B11 -> 13271 | C18: ='Balance Sheet'!C11 -> 9769 | D18: ='Balance Sheet'!D11 -> 9740 | E18: Balance Sheet
A19: Accounts Receivable | B19: ='Balance Sheet'!B10 -> 5158 | C19: ='Balance Sheet'!C10 -> 4304 | D19: ='Balance Sheet'!D10 -> 3916 | E19: Balance Sheet
A20: Total Assets | B20: ='Balance Sheet'!B17 -> 169998 | C20: ='Balance Sheet'!C17 -> 138615 | D20: ='Balance Sheet'!D17 -> 123211 | E20: Balance Sheet
A21: Total Liabilities | B21: ='Balance Sheet'!B27 -> 108456 | C21: ='Balance Sheet'!C27 -> 89260 | D21: ='Balance Sheet'!D27 -> 81971 | E21: Balance Sheet
A22: Total Equity | B22: ='Balance Sheet'!B31 -> 56115 | C22: ='Balance Sheet'!C31 -> 47664 | D22: ='Balance Sheet'!D31 -> 39500 | E22: Balance Sheet
A23: Goodwill & Intangible Assets, Net | B23: ='Balance Sheet'!B16 -> 63251 | C23: ='Balance Sheet'!C16 -> 46692 | D23: ='Balance Sheet'!D16 -> 33782 | E23: Balance Sheet
A25: Section 3 - Cash Flow Inputs
A26: Metric | B26: FY 2025 | C26: FY 2024 | D26: FY 2023 | E26: Formula/Source
A27: Operating Cash Flow | B27: ='Cash Flow Statement'!B16 -> 3927 | C27: ='Cash Flow Statement'!C16 -> 4956 | D27: ='Cash Flow Statement'!D16 -> 4165 | E27: Cash Flow Statement
A28: Capital Expenditures | B28: ='Cash Flow Statement'!B23 -> -375 | C28: ='Cash Flow Statement'!C23 -> -255 | D28: ='Cash Flow Statement'!D23 -> -344 | E28: Cash Flow Statement
A29: Free Cash Flow | B29: =SUM(B27:B28) -> 3552 | C29: =SUM(C27:C28) -> 4701 | D29: =SUM(D27:D28) -> 3821 | E29: Calculated
A30: Investing Cash Flow | B30: ='Cash Flow Statement'!B24 -> -4418 | C30: ='Cash Flow Statement'!C24 -> -3004 | D30: ='Cash Flow Statement'!D24 -> -959 | E30: Cash Flow Statement
A31: Financing Cash Flow | B31: ='Cash Flow Statement'!B31 -> -1127 | C31: ='Cash Flow Statement'!C31 -> 2236 | D31: ='Cash Flow Statement'!D31 -> -1992 | E31: Cash Flow Statement
A32: Ending Cash Balance | B32: ='Cash Flow Statement'!B36 -> 11490 | C32: ='Cash Flow Statement'!C36 -> 12779 | D32: ='Cash Flow Statement'!D36 -> 8753 | E32: Cash Flow Statement

Sheet Ratio Analysis
C2: BlackRock, Inc. (NYSE: BLK)
C3: Financial Ratio Analysis
C4: Fiscal Years 2025, 2024, and 2023
A6: Ratio | B6: Formula | C6: FY2025 | D6: FY2024 | E6: FY2023 | F6: Analysis
A7: PROFITABILITY RATIOS
A8: Revenue Growth | B8: (Current Revenue − Previous Revenue) / Previous Revenue | C8: =('Income Statement'!B13-'Income Statement'!C13)/'Income Statement'!C13 -> 0.18665164 | D8: =('Income Statement'!C13-'Income Statement'!D13)/'Income Statement'!D13 -> 0.14267316 | E8: N/M | F8: Revenue growth accelerated to 18.7% in FY2025 from 14.3% in FY2024, driven by higher investment advisory, technology services, and acquisition-related revenue contributions.
A9: Operating Margin | B9: Operating Income / Total Revenue | C9: ='Income Statement'!B23/'Income Statement'!B13 -> 0.29092336 | D9: ='Income Statement'!C23/'Income Statement'!C13 -> 0.37114716 | E9: ='Income Statement'!D23/'Income Statement'!D13 -> 0.35136346 | F9: Operating margin declined to 29.1% from 37.1%, reflecting higher operating expenses and acquisition-related costs despite strong revenue growth.
A10: Net Profit Margin | B10: Net Income / Total Revenue | C10: ='Income Statement'!B30/'Income Statement'!B13 -> 0.24537496 | D10: ='Income Statement'!C30/'Income Statement'!C13 -> 0.31910619 | E10: ='Income Statement'!D30/'Income Statement'!D13 -> 0.31782295 | F10: Net profit margin decreased to 24.5%, indicating that net income grew more slowly than revenue due to higher expenses and integration costs.
A11: Return on Assets (ROA) | B11: Net Income / Average Total Assets | C11: ='Income Statement'!B30/AVERAGE('Balance Sheet'!B17,'Balance Sheet'!C17) -> 0.038507775 | D11: ='Income Statement'!C30/AVERAGE('Balance Sheet'!C17,'Balance Sheet'!D17) -> 0.049742959 | E11: N/M | F11: ROA declined to 3.9%, reflecting lower profitability relative to the expanded asset base following strategic acquisitions.
A12: Return on Equity (ROE) | B12: Net Income / Average Total Equity | C12: ='Income Statement'!B30/AVERAGE('Balance Sheet'!B31,'Balance Sheet'!C31) -> 0.11451257 | D12: ='Income Statement'!C30/AVERAGE('Balance Sheet'!C31,'Balance Sheet'!D31) -> 0.14941949 | E12: N/M | F12: ROE declined to 11.5%, reflecting lower profitability relative to the equity base following strategic acquisitions.
A14: LIQUIDITY RATIOS
A15: Cash Ratio | B15: Cash & Cash Equivalents / Total Liabilities | C15: ='Balance Sheet'!B9/'Balance Sheet'!B27 -> 0.10573873 | D15: ='Balance Sheet'!C9/'Balance Sheet'!C27 -> 0.14297558 | E15: ='Balance Sheet'!D9/'Balance Sheet'!D27 -> 0.10657428 | F15: Cash ratio remained relatively stable at 0.11x, indicating adequate short-term liquidity despite increased investment and acquisition activity.
A17: LEVERAGE RATIOS
A18: Debt Ratio | B18: Total Liabilities / Total Assets | C18: ='Balance Sheet'!B27/'Balance Sheet'!B17 -> 0.63798398 | D18: ='Balance Sheet'!C27/'Balance Sheet'!C17 -> 0.64394185 | E18: ='Balance Sheet'!D27/'Balance Sheet'!D17 -> 0.66528963 | F18: Debt ratio improved slightly to 63.8%, suggesting a modest reduction in leverage relative to total assets.
A19: Equity Ratio | B19: Total Equity / Total Assets | C19: ='Balance Sheet'!B31/'Balance Sheet'!B17 -> 0.33009212 | D19: ='Balance Sheet'!C31/'Balance Sheet'!C17 -> 0.34385889 | E19: ='Balance Sheet'!D31/'Balance Sheet'!D17 -> 0.32058826 | F19: Equity ratio remained solid at 33.0%, demonstrating continued shareholder support for BlackRock's asset base.
A20: Debt-to-Equity | B20: Total Liabilities / Total Equity | C20: ='Balance Sheet'!B27/'Balance Sheet'!B31 -> 1.9327453 | D20: ='Balance Sheet'!C27/'Balance Sheet'!C31 -> 1.8726922 | E20: ='Balance Sheet'!D27/'Balance Sheet'!D31 -> 2.0752152 | F20: Debt-to-equity increased slightly to 1.93x, reflecting higher liabilities associated with acquisition financing while maintaining a balanced capital structure.
A22: EFFICIENCY RATIOS
A23: Asset Turnover | B23: Revenue / Average Total Assets | C23: ='Income Statement'!B13/AVERAGE('Balance Sheet'!B17,'Balance Sheet'!C17) -> 0.15693441 | D23: ='Income Statement'!C13/AVERAGE('Balance Sheet'!C17,'Balance Sheet'!D17) -> 0.15588215 | E23: N/M | F23: Asset turnover remained stable at 0.16x, indicating consistent efficiency in generating revenue from total assets.
A24: Receivables Turnover | B24: Revenue / Average Accounts Receivable | C24: ='Income Statement'!B13/AVERAGE('Balance Sheet'!B10,'Balance Sheet'!C10) -> 5.1185796 | D24: ='Income Statement'!C13/AVERAGE('Balance Sheet'!C10,'Balance Sheet'!D10) -> 4.9652068 | E24: N/M | F24: Receivables turnover improved to 5.12x, reflecting faster collection of receivables and improved working capital management.
A26: CASH FLOW RATIOS
A27: Operating Cash Flow Margin | B27: Operating Cash Flow / Revenue | C27: ='Cash Flow Statement'!B16/'Income Statement'!B13 -> 0.16216551 | D27: ='Cash Flow Statement'!C16/'Income Statement'!C13 -> 0.24285784 | E27: ='Cash Flow Statement'!D16/'Income Statement'!D13 -> 0.23321575 | F27: Operating cash flow margin declined to 16.2%, primarily due to higher working capital requirements and acquisition-related cash adjustments.
A28: Free Cash Flow Margin | B28: Free Cash Flow / Revenue | C28: =('Cash Flow Statement'!B16-'Cash Flow Statement'!B23)/'Income Statement'!B13 -> 0.17765114 | D28: =('Cash Flow Statement'!C16-'Cash Flow Statement'!C23)/'Income Statement'!C13 -> 0.25535356 | E28: =('Cash Flow Statement'!D16-'Cash Flow Statement'!D23)/'Income Statement'!D13 -> 0.25247774 | F28: Free cash flow margin decreased to 17.8%, reflecting increased capital deployment toward acquisitions and strategic investments during FY2025.
A32: Executive Summary: • Revenue growth accelerated to 18.7% in FY2025, supported by strong organic business performance and contributions from strategic acquisitions. • Profitability moderated as operating margin (29.1%) and net profit margin (24.5%) declined due to higher operating expenses and acquisition-related integration costs. • Liquidity remained healthy, with a cash ratio of 0.11x, providing sufficient financial flexibility to support ongoing operations and investments. • Leverage remained well managed, with a 63.8% debt ratio and 1.93x debt-to-equity ratio, reflecting a balanced capital structure despite acquisition financing. • Operating efficiency remained stable, while receivables turnover improved to 5.12x, indicating effective working capital management. • Although operating and free cash flow margins declined, BlackRock continued to generate strong operating cash flows, supporting long-term strategic investments and shareholder returns.
A34: Overall Analysis: BlackRock's financial ratios demonstrate that the company maintained a strong financial position throughout FY2025 while continuing to invest in long-term growth initiatives. Revenue growth strengthened significantly, supported by strategic acquisitions and expansion across its investment management platform. Although profitability and cash flow margins moderated due to acquisition-related expenses and integration costs, the company preserved healthy liquidity, maintained a balanced capital structure, and continued operating efficiently. Overall, the ratio analysis reflects BlackRock's financial resilience, disciplined capital allocation, and ability to support sustainable long-term shareholder value.

Sheet Financial Charts
M2: BlackRock, Inc. (NYSE: BLK)
M3: Financial Charts & Visual Analysis
M4: Fiscal Years 2025, 2024, and 2023
A6: Revenue vs Net Income | O6: Assets vs. Liabilities & Equity
A7: Year | B7: Revenue | C7: Net Income | O7: Year | P7: Total Assets | Q7: Total Liabilities | R7: Total Equity
A8: 2023 | B8: 17859 | C8: 5676 | O8: 2023 | P8: 123211 | Q8: 81971 | R8: 39500
A9: 2024 | B9: 20407 | C9: 6512 | O9: 2024 | P9: 138615 | Q9: 89260 | R9: 47664
A10: 2025 | B10: 24216 | C10: 5942 | O10: 2025 | P10: 169998 | Q10: 108456 | R10: 56115
A25: Profitability Margins Trend | O25: Cash Flow Performance
A26: Year | B26: Operating Margin | C26: Net Profit Margin | O26: Year | P26: Operating Cash Flow | Q26: Investing Cash Flow | R26: Financing Cash Flow
A27: 2023 | B27: 0.351 | C27: 0.318 | O27: 2023 | P27: 4165 | Q27: -959 | R27: -1992
A28: 2024 | B28: 0.371 | C28: 0.319 | O28: 2024 | P28: 4956 | Q28: -3004 | R28: 2236
A29: 2025 | B29: 0.291 | C29: 0.245 | O29: 2025 | P29: 3927 | Q29: -4418 | R29: -1127
A46: Efficiency Ratios | O46: Relative Valuation — BlackRock vs. Selected Peers
A47: Year | B47: Asset Turnover | C47: Receivables Turnover | O47: Company | P47: Adjusted P/E | Q47: Peer Median
A48: 2024 | B48: 0.15 | C48: 4.97 | O48: BlackRock | P48: 24.41 | Q48: 15.25
A49: 2025 | B49: 0.14 | C49: 5.12 | O49: T. Rowe Price | P49: 11.37 | Q49: 15.25
O50: Franklin Resources | P50: 15.25 | Q50: 15.25
O51: Invesco | P51: 16.03 | Q51: 15.25

Sheet Dashboard
E2: BlackRock, Inc. (NYSE: BLK)
E3: Financial Performance Dashboard
E4: Fiscal Years 2025, 2024, and 2023
E5: All amounts in millions of U.S. dollars, except per-share and ratio data.
A7: FY2025 KPI cards
A36: Year | B36: Revenue | C36: Net Income
A37: 2023 | B37: 17859 | C37: 5502
A38: 2024 | B38: 20407 | C38: 6369
A39: 2025 | B39: 24216 | C39: 5553
A52: 3-Year Financial Performance Analysis
A53: Metric | B53: FY2023 | C53: FY2024 | D53: FY2025 | E53: 2024 YoY | F53: 2025 YoY
A54: Revenue | B54: 17859 | C54: 20407 | D54: 24216 | E54: =(C54/B54)-1 -> 0.14267316 | F54: =(D54/C54)-1 -> 0.18665164
A55: Operating Income | B55: 6275 | C55: 7574 | D55: 7045 | E55: =(C55/B55)-1 -> 0.20701195 | F55: =(D55/C55)-1 -> -0.069844204
A56: Net Income Attributable to BLK | B56: 5502 | C56: 6369 | D56: 5553 | E56: =(C56/B56)-1 -> 0.15757906 | F56: =(D56/C56)-1 -> -0.12812058
A57: Diluted EPS | B57: 36.51 | C57: 42.01 | D57: 35.31 | E57: =(C57/B57)-1 -> 0.15064366 | F57: =(D57/C57)-1 -> -0.15948584
A58: Operating Margin | B58: =B55/B54 -> 0.35136346 | C58: =C55/C54 -> 0.37114716 | D58: =D55/D54 -> 0.29092336 | E58: =(C58-B58)*10000 -> 197.83697 | F58: =(D58-C58)*10000 -> -802.23799
A59: Net Margin | B59: =B56/B54 -> 0.30807996 | C59: =C56/C54 -> 0.31209879 | D59: =D56/D54 -> 0.2293112 | E59: =(C59-B59)*10000 -> 40.188299 | F59: =(D59-C59)*10000 -> -827.8759
A62: Key Financial Takeaways:
A63: 1. Strong top-line growth
A64: Revenue increased 18.7% YoY to $24.2B in FY2025, accelerating from 14.3% growth in FY2024.
A66: 2. Profitability weakened despite revenue growth
A67: Operating income declined 7.0% and net income attributable to BLK declined 12.8% in FY2025, while operating margin contracted 802 bps to 29.1%.
A69: 3. EPS experienced greater pressure
A70: Diluted EPS declined 15.9% to $35.31, outpacing the 12.8% decline in net income attributable to BLK and indicating greater pressure on per-share earnings despite strong revenue growth.
A72: 4. AUM growth remained strong
A73: Total AUM increased 21.6% YoY to $14.0T in FY2025, accelerating from 15.4% growth in FY2024 and supporting BlackRock's expanding revenue-generating asset base.
A75: AUM Growth Analysis:
A76: Year | B76: Total AUM ($T) | C76: YoY Growth
A77: 2023 | B77: 10.009 | C77: -
A78: 2024 | B78: 11.551 | C78: =(B78/B77)-1 -> 0.15406134
A79: 2025 | B79: 14.042 | C79: =(B79/B78)-1 -> 0.21565232
A81: AUM expanded from $10.0T in FY2023 to $14.0T in FY2025, with growth accelerating to 21.6% in FY2025, supporting BlackRock's expanding asset base and revenue-generating capacity.

Sheet Valuation
C2: BlackRock Relative Valuation & Sensitivity Analysis
A4: BlackRock Relative Valuation
A5: Company | B5: Aug. 14 Price | C5: FY2025 GAAP EPS | D5: FY2025 Adjusted EPS | E5: P/E
A6: BlackRock | B6: 1173.73 | C6: 35.31 | D6: 48.09 | E6: =B6/D6 -> 24.406945
A7: T. Rowe Price | B7: 110.56 | C7: 9.24 | D7: 9.72 | E7: =B7/D7 -> 11.374486
A8: Franklin Resources | B8: 33.86 | C8: 0.91 | D8: 2.22 | E8: =B8/D8 -> 15.252252
A9: Invesco | B9: 32.55 | C9: -1.6 | D9: 2.03 | E9: =B9/D9 -> 16.034483
A10: Peer Median | E10: =MEDIAN(E7:E9) -> 15.252252
A13: BlackRock Implied Valuation
A14: FY2025 Adjusted EPS | B14: 48.09
A15: Peer Median P/E | B15: 15.25x
A16: Implied Share Price | B16: =D6*E10 -> 733.48081
A17: Aug. 14 BLK Price | B17: 1173.73
A18: Implied Upside / (Downside) | B18: =(B16/B6)-1 -> -0.37508557
A21: P/E Sensitivity Analysis
A22: P/E Multiple | B22: Implied Share Price | C22: Upside / (Downside)
A23: 15 | B23: =A23*$D$6 -> 721.35 | C23: =(B23/$B$6)-1 -> -0.38542084
A24: 17.5 | B24: =A24*$D$6 -> 841.575 | C24: =(B24/$B$6)-1 -> -0.28299098
A25: 20 | B25: =A25*$D$6 -> 961.8 | C25: =(B25/$B$6)-1 -> -0.18056112
A26: 22.5 | B26: =A26*$D$6 -> 1082.025 | C26: =(B26/$B$6)-1 -> -0.078131257
A27: 25 | B27: =A27*$D$6 -> 1202.25 | C27: =(B27/$B$6)-1 -> 0.024298604
A30: BlackRock P/B Relative Valuation
A31: Company | B31: Aug. 14 2026, Closing Price | C31: FY2025 Book Value / Share | D31: P/B
A32: BlackRock | B32: 1173.73 | C32: 360.41 | D32: =B32/C32 -> 3.2566521
A33: T. Rowe Price | B33: 110.56 | C33: 49.68 | D33: =B33/C33 -> 2.2254428
A34: Franklin Resources | B34: 33.86 | C34: 23.18 | D34: =B34/C34 -> 1.460742
A35: Invesco | B35: 32.55 | C35: 9.721 | D35: =B35/C35 -> 3.3484209
A36: Peer Median | D36: =MEDIAN(D33:D35) -> 2.2254428
A39: VALUATION SUMMARY
A40: Metric | B40: BlackRock | C40: Peer Median | D40: BLK Premium
A41: Adjusted P/E | B41: 24.41 | C41: 15.25 | D41: =(B41/C41)-1 -> 0.60065574
A42: P/B | B42: 3.26 | C42: 2.23 | D42: =(B42/C42)-1 -> 0.46188341

Sheet Key Insights
D2: BLACKROCK — KEY INVESTMENT INSIGHTS
D3: FY2025 Financial Performance, Operating Trends & Relative Valuation
A5: 1. AUM Expansion Supports Strong Top-Line Momentum
A7: BlackRock generated 18.7% year-over-year revenue growth to $24.2B in FY2025, alongside 21.6% growth in AUM to approximately $14.0T. The expansion in the asset base reinforces the firm's scale advantage and provides a strong foundation for fee-generating revenue growth.
A9: 2. Earnings Conversion Lagged Operating Momentum
A11: Strong top-line growth did not translate proportionately into GAAP earnings growth, with operating income declining 7.0% and net income attributable to BlackRock declining 12.8%. Operating margin contracted approximately 802 bps to 29.1%, highlighting weaker earnings conversion despite significant AUM and revenue expansion.
A13: 3. Market Assigns BlackRock a Material Premium to Selected Peers
A15: BlackRock trades at 24.41x FY2025 adjusted diluted EPS versus a 15.25x selected-peer median, representing an approximately 60.1% premium. Its 3.26x P/B multiple similarly exceeds the 2.23x peer median by approximately 46.2%, indicating that investors are assigning a meaningful premium to BlackRock relative to the selected traditional asset-management peer set.
A17: 4. Relative Valuation Highlights the Multiple Embedded in the Current Price
A19: Applying the 15.25x selected-peer median P/E to BlackRock's FY2025 adjusted diluted EPS implies a value of approximately $733 per share versus the $1,173.73 August 14 closing price. Sensitivity analysis across a 15.0x–25.0x P/E range produces implied values of approximately $721–$1,202 per share, indicating that the prevailing market price requires a valuation multiple near the upper end of the analyzed range.
A21: INVESTMENT VIEW:
A23: BlackRock's FY2025 performance reflects strong underlying business momentum, supported by substantial AUM expansion and accelerating revenue growth, while weaker GAAP earnings conversion and margin compression remain key considerations. The shares trade at meaningful P/E and P/B premiums to the selected peer group, indicating that the market is pricing in sustained growth and superior business quality. The investment case therefore depends on BlackRock's ability to convert continued asset growth and scale advantages into stronger earnings and margin performance sufficient to justify its premium valuation relative to the selected peer group.

Sheet Sources
B2: Sources & References
B3: Primary company filings, investor materials, and market data sources used in the analysis.
A6: Source | B6: Information Used | C6: Period / Data | D6: URL
A7: BlackRock Annual Reports | B7: Income statement, balance sheet, cash flow, AUM, operating results and company disclosures | C7: FY2023–FY2025 | D7: Link
A8: BlackRock Investor Relations | B8: Earnings materials, investor information and company disclosures | C8: FY2023–FY2025 | D8: Link
A9: SEC Filings / Form 10-K | B9: Regulatory filings and verification of reported financial information | C9: FY2023–FY2025 | D9: Link
A10: Yahoo Finance — BLK | B10: Share price and market/valuation data | C10: Market data | D10: Link
A11: Macrotrends — BLK | B11: Historical financial data used for cross-checking | C11: Historical data | D11: Link
